{
	"resources" : [ "m0", "m1", "m2", "m3" ],
	"tasks" : {
		"t0" : { 
		       "exec" : 1000, 
		       "period" : 10000, 
		       "deadline" : 8000, 
		       "cpu" : [0,1], 
		       "policy" : "SCHED_FIFO", 
		       "lock" : [ "m1" ],
		       "resources" : {
			   "m1" : { "duration" : 1000 }
		       }
		},
		"t1" : { 
		       "exec" : 50000, 
		       "period" : 100000, 
		       "cpu" : [1], 
		       "policy" : "SCHED_DEADLINE",
		       "lock" : [ "m0", "m3", "m2" ],
		       "resources": {
			   "m0" : { "duration" : 1000, "access": ["m2"] },
			   "m1" : { "duration" : 100, "access": ["m3"] },
			   "m2" : { "duration" : 200, "access": ["m1"] },
			   "m3" : { "duration" : 500}
		       }	
		}
	},
	"global" : {
		"spacing" : 0,
		"default_policy" : "SCHED_OTHER",
		"duration" : -1,
		"gnuplot" : false,
		"logdir" : null,
		"log_basename" : "rt-app",
		"lock_pages" : true,
		"frag" : 1
	}
}
